rowan_ds_tools/__init__.py
rowan_ds_tools/EDA/__init__.py
rowan_ds_tools/EDA/nlp_eda.py
rowan_ds_tools/Random/EDA_functins.py
rowan_ds_tools/Random/__init__.py
rowan_ds_tools/Random/data_cleaning_functions.py
rowan_ds_tools/io/GCP_bucket.py
rowan_ds_tools/io/__init__.py
rowan_ds_tools/io/db_helper.py
rowan_ds_tools/io/tests/test_db_helper.py
rowan_ds_tools/utils/__init__.py
rowan_ds_tools/utils/_param_validation.py
rowan_ds_tools/utils/logger_tools.py
rowan_ds_tools-0.14.dist-info/LICENSE
rowan_ds_tools-0.14.dist-info/METADATA
rowan_ds_tools-0.14.dist-info/WHEEL
rowan_ds_tools-0.14.dist-info/top_level.txt
rowan_ds_tools-0.14.dist-info/RECORD
